{//扶贫任务
	"pyAlleMission":{//搬迁
		"documentHouses":135,//建档户数
		"documentPersons":350,//建档人数
		"targetPersonsCount":175, //目标人数
		"percentage":"4.5%" //完成度
	},
	"civilAdministration":{//民政
		"poorHouses":1829,//贫困人口户数
		"poorPersons":3103,//贫困人口数
		"percentage":"4.5%" //完成度
	},
	"medicalCare":{//医疗
		"poorPersons":15383,//贫困人口数
		"percentage":"23.3%" //完成度
	},
	"education":{//教育
		"projectCount":10,//项目个数
		"areaStructure":39900,//建筑面积
		"investment":17909,//总投资
		"percentage":"4.5%" //完成度
	},
	"industry":{//产业
		"investment":15428,//资金
		"housesCount":1480,//户数
		"personCount":3450,//人数
		"percentage":"4.5%" //完成度
	}
}	